{
	"id": 2,
	"item_name": "★씬님&조효진추천★바이오힐보 프로바이오덤 리프팅크림 더블기획50*2",
	"brand": "바이오힐보",
	"category": "스킨케어>페이셜케어>크림",
	"volume": "■크림50mLX2",
	"elements": [
		"정제수",
		" 락토바실러스발효물",
		" 다이프로필렌글라이콜",
		" 글리세린",
		" 카프릴릭/카프릭트라이글리세라이드",
		"\n하이드로제네이티드폴리(C6-14올레핀)",
		" 하이드로제네이티드폴리데센",
		" 글리세릴스테아레이트",
		" 1",
		"2-헥산다이올",
		" 하이드로제네이티드식물성오일",
		" 메도우폼씨오일",
		" 나이아신아마이드",
		" 폴리글리세릴-3메틸글루코오스다이스테아레이트",
		" 세테아릴알코올",
		" 펜틸렌글라이콜",
		" 호호바에스터",
		" 수크로오스",
		" 시어버터",
		" 바실러스발효물",
		" 한련초추출물",
		" 인도멀구슬나무꽃추출물",
		" 인도멀구슬나무잎추출물",
		" 카카오씨추출물",
		" 울금뿌리추출물",
		" 홀리바질잎추출물",
		" 자일로오스",
		" 참산호말추출물",
		" 드럼스틱씨오일",
		" 리마콩씨추출물",
		" 칸디다 봄비콜라/글루코오스/메틸레이프씨데이트발효물",
		" 올리브오일",
		" 다이펜타에리스리틸헥사하이드록시스테아레이트/헥사스테아레이트/헥사로지네이트",
		" 폴리메틸실세스퀴옥세인",
		" 폴리솔베이트60",
		" 세테아릴올리베이트",
		" 피이지-100스테아레이트",
		" 솔비탄올리베이트",
		" 다이메티콘",
		" 카프릴릴글라이콜",
		" 마이크로코쿠스용해물",
		" 트로메타민",
		" 토코페릴아세테이트",
		" 에틸헥실글리세린",
		" 아데노신",
		" 다이포타슘글리시리제이트",
		" 부틸렌글라이콜",
		" 프룩토오스",
		" 덱스트린",
		" 세라마이드엔피",
		" 하이드로제네이티드레시틴",
		" 토코페롤",
		" 다이펩타이드다이아미노부티로일벤질아마이드다이아세테이트",
		" 팔미토일트라이펩타이드-5",
		" 세틸하이드록시에틸셀룰로오스",
		" 루틴",
		" 헥사펩타이드-2",
		" 아세틸테트라펩타이드-5",
		" 덱스트란",
		" 트라이펩타이드-1",
		" 팔미토일헥사펩타이드-12",
		" 바이오틴",
		" 아세틸헥사펩타이드-8",
		" 팔미토일테트라펩타이드-7",
		" 팔미토일트라이펩타이드-1",
		" 팔미토일펜타펩타이드-4",
		" 헥사펩타이드-9",
		" 카퍼트라이펩타이드-1",
		" 세테아레스-20",
		" 콜레스테롤",
		" 글라이코리피드",
		" 레시틴",
		" 올레익애씨드",
		" 피이지-40하이드로제네이티드캐스터오일",
		" 포타슘하이드록사이드",
		" 베헤닐알코올",
		" 카보머",
		" 잔탄검",
		" 다이소듐이디티에이",
		" 향료"
	]
}